matplotlibe/__init__.py
matplotlibe/main.py
matplotlibe-1.0.0.dist-info/METADATA
matplotlibe-1.0.0.dist-info/WHEEL
matplotlibe-1.0.0.dist-info/top_level.txt
matplotlibe-1.0.0.dist-info/RECORD
